pysforce/__init__.py
pysforce/auth.py
pysforce/sfapi.py
pysforce-1.1.2.dist-info/LICENSE
pysforce-1.1.2.dist-info/METADATA
pysforce-1.1.2.dist-info/WHEEL
pysforce-1.1.2.dist-info/top_level.txt
pysforce-1.1.2.dist-info/RECORD
