Metadata-Version: 2.1
Name: pysforce
Version: 1.1.2
Summary: Salesforce API library
Home-page: https://github.com/mlsmithjr/pysforce
Author: Marshall L Smith Jr
Author-email: marshallsmithjr@gmail.com
License: UNKNOWN
Platform: UNKNOWN
Classifier: Programming Language :: Python :: 3
Classifier: Environment :: Console
Classifier: License :: OSI Approved :: GNU General Public License v3 (GPLv3)
Classifier: Natural Language :: English
Requires-Python: >=3.6
Requires-Dist: requests
Requires-Dist: pyjwt
Requires-Dist: cryptography
Requires-Dist: fastcache
